LICENSE
README.md
setup.py
pypelineer/__init__.py
pypelineer.egg-info/PKG-INFO
pypelineer.egg-info/SOURCES.txt
pypelineer.egg-info/dependency_links.txt
pypelineer.egg-info/top_level.txt
pypelineer/cores/__init__.py
pypelineer/cores/_impl/__init__.py
pypelineer/cores/_impl/_functools.py
pypelineer/cores/_impl/_templates.py
pypelineer/cores/_impl/abtract.py
pypelineer/cores/_impl/egress.py
pypelineer/cores/_impl/funnel.py
pypelineer/cores/_impl/ingress.py
pypelineer/cores/_impl/junction.py
pypelineer/cores/_impl/process.py
pypelineer/nodes/__init__.py
pypelineer/nodes/_impl/__init__.py
pypelineer/nodes/_impl/abtract.py
pypelineer/nodes/_impl/egress.py
pypelineer/nodes/_impl/funnel.py
pypelineer/nodes/_impl/ingress.py
pypelineer/nodes/_impl/junction.py
pypelineer/nodes/_impl/process.py
pypelineer/prefabs/__init__.py
pypelineer/prefabs/_impl/__init__.py
pypelineer/tasks/__init__.py