Metadata-Version: 2.1
Name: pypelineer
Version: 0.0.4
Summary: Simplistic library for building pipelines efficiently and fast.
Home-page: https://github.com/sadigaxund/pypeliner
Author: Sadig Akhund
Author-email: sadigaxund@gmail.com
Project-URL: Bug Tracker, https://github.com/sadigaxund/pypeliner/issues
Project-URL: Documentation, https://github.com/sadigaxund/pypeliner/blob/main/README.md
Project-URL: Source Code, https://github.com/sadigaxund/pypeliner
Keywords: your keywords here
Classifier: Development Status :: 5 - Production/Stable
Classifier: Programming Language :: Python :: 3
Classifier: License :: OSI Approved :: Apache Software License
Classifier: Operating System :: OS Independent
Requires-Python: >=3.8
License-File: LICENSE
